aggregate_prefixes/__about__.py
aggregate_prefixes/__init__.py
aggregate_prefixes/__main__.py
aggregate_prefixes/aggregate_prefixes.py
aggregate_prefixes-0.7.2.dist-info/LICENSE
aggregate_prefixes-0.7.2.dist-info/METADATA
aggregate_prefixes-0.7.2.dist-info/WHEEL
aggregate_prefixes-0.7.2.dist-info/entry_points.txt
aggregate_prefixes-0.7.2.dist-info/RECORD
