Metadata-Version: 2.1
Name: aggregate-prefixes
Version: 0.7.2
Summary: 
Home-page: https://github.com/lamehost/aggregate-prefixes
Author: Marco Marzetti
Author-email: marco@lamehost.it
Requires-Python: >=3.9,<4.0
Classifier: Programming Language :: Python :: 3
Classifier: Programming Language :: Python :: 3.9
Classifier: Programming Language :: Python :: 3.10
Classifier: Programming Language :: Python :: 3.11
Classifier: Programming Language :: Python :: 3.12
